{
	"id": "124772",
	"fullName": "Alberto CIRIO",
	"countryCode": "it",
	"countryLabel": "Italy",
	"countryFlag": "http://www.europarl.europa.eu/ep_framework/img/flag/flag_icon_it.gif",
	"politicalGroupCode": "epp",
	"politicalGroupLabel": "Group of the European People's Party (Christian Democrats)",
	"politicalGroupIcon": "http://www.europarl.europa.eu/ep_framework/img/group/group_icon_epp.png",
	"nationalPoliticalGroupLabel": "Forza Italia",
	"email": "alberto.cirio@europarl.europa.eu",
	"twitterUrl": "https://twitter.com/Alberto_Cirio",
	"twitterProfile": "Alberto_Cirio",
	"roles": [
		{
			"Substitute": "Committee on Agriculture and Rural Development"
		},
		{
			"Member": "Committee on the Environment, Public Health and Food Safety"
		}
	]
}