{
	"id": "23868",
	"fullName": "Monika FLAŠÍKOVÁ BEŇOVÁ",
	"countryCode": "sk",
	"countryLabel": "Slovakia",
	"countryFlag": "http://www.europarl.europa.eu/ep_framework/img/flag/flag_icon_sk.gif",
	"politicalGroupCode": "sd",
	"politicalGroupLabel": "Group of the Progressive Alliance of Socialists and Democrats in the European Parliament",
	"politicalGroupIcon": "http://www.europarl.europa.eu/ep_framework/img/group/group_icon_sd.png",
	"nationalPoliticalGroupLabel": "SMER-Sociálna demokracia",
	"email": "monika.flasikovabenova@europarl.europa.eu",
	"webPage": "http://monikaflasikovabenova.sk/",
	"facebookPageUrl": "https://www.facebook.com/pages/Monika-Fla%C5%A1%C3%ADkov%C3%A1-Be%C5%88ov%C3%A1/253595649968?sk=wall",
	"roles": [
		{
			"Member": "European Parliament"
		},
		{
			"Substitute": "Delegation for relations with Israel"
		}
	]
}