{
	"id": "28394",
	"fullName": "Dariusz ROSATI",
	"countryCode": "pl",
	"countryLabel": "Poland",
	"countryFlag": "http://www.europarl.europa.eu/ep_framework/img/flag/flag_icon_pl.gif",
	"politicalGroupCode": "epp",
	"politicalGroupLabel": "Group of the European People's Party (Christian Democrats)",
	"politicalGroupIcon": "http://www.europarl.europa.eu/ep_framework/img/group/group_icon_epp.png",
	"nationalPoliticalGroupLabel": "Platforma Obywatelska",
	"email": "dariusz.rosati@europarl.europa.eu",
	"twitterUrl": "https://twitter.com/DariuszRosati",
	"roles": [
		{
			"Member": "European Parliament"
		},
		{
			"Substitute": "Delegation for relations with the United States"
		}
	]
}