{
	"id": "4513",
	"fullName": "Geoffrey VAN ORDEN",
	"countryCode": "gb",
	"countryLabel": "United Kingdom",
	"countryFlag": "http://www.europarl.europa.eu/ep_framework/img/flag/flag_icon_gb.gif",
	"politicalGroupCode": "ecr",
	"politicalGroupLabel": "European Conservatives and Reformists Group",
	"politicalGroupIcon": "http://www.europarl.europa.eu/ep_framework/img/group/group_icon_ecr.png",
	"nationalPoliticalGroupLabel": "Conservative Party",
	"email": "geoffrey.vanorden@europarl.europa.eu",
	"roles": [
		{
			"Member": "Committee on Foreign Affairs"
		},
		{
			"Chair": "Delegation for relations with India"
		},
		{
			"Substitute": "Committee on Employment and Social Affairs"
		},
		{
			"Vice-Chair": "European Conservatives and Reformists Group"
		}
	]
}